Workbook

Sheet Raw Data - Suppliers
A1: supplier | B1: quality | C1: quantity | D1: conditions and method of payment | E1: serviceability and communicativeness of the supplier | F1: reputation of the supplier and its competence | G1: flexibility | H1: financial condition of the supplier | I1: condition of the supplier's assets | J1: business results and number of employees | K1: price | L1: delivery time | M1: supplier's location and traffic connections
A2: 1 | B2: 4 | C2: 350 | D2: 3 | E2: 3 | F2: 4 | G2: 4 | H2: 4 | I2: 3 | J2: 5 | K2: 5 | L2: 2 | M2: 50
A3: 2 | B3: 2 | C3: 350 | D3: 2 | E3: 5 | F3: 4 | G3: 3 | H3: 5 | I3: 4 | J3: 6 | K3: 7 | L3: 3 | M3: 60
A4: 3 | B4: 2 | C4: 450 | D4: 3 | E4: 6 | F4: 5 | G4: 4 | H4: 7 | I4: 8 | J4: 9 | K4: 8 | L4: 4 | M4: 30
A5: 4 | B5: 4 | C5: 260 | D5: 3 | E5: 6 | F5: 8 | G5: 5 | H5: 7 | I5: 8 | J5: 9 | K5: 7 | L5: 1 | M5: 40
A6: 5 | B6: 3 | C6: 170 | D6: 3 | E6: 7 | F6: 6 | G6: 2 | H6: 6 | I6: 5 | J6: 4 | K6: 7 | L6: 2 | M6: 35
A7: 6 | B7: 4 | C7: 180 | D7: 1 | E7: 8 | F7: 8 | G7: 2 | H7: 9 | I7: 7 | J7: 5 | K7: 8 | L7: 0.5 | M7: 55
A8: 7 | B8: 3 | C8: 350 | D8: 1 | E8: 3 | F8: 4 | G8: 4 | H8: 4 | I8: 3 | J8: 5 | K8: 5 | L8: 2 | M8: 62
A9: 8 | B9: 3 | C9: 250 | D9: 1 | E9: 6 | F9: 5 | G9: 3 | H9: 6 | I9: 5 | J9: 4 | K9: 6 | L9: 4 | M9: 78
A10: 9 | B10: 5 | C10: 360 | D10: 4 | E10: 9 | F10: 8 | G10: 5 | H10: 8 | I10: 6 | J10: 5 | K10: 6 | L10: 3 | M10: 120
A11: 10 | B11: 4 | C11: 240 | D11: 4 | E11: 9 | F11: 8 | G11: 3 | H11: 8 | I11: 6 | J11: 6 | K11: 7 | L11: 1 | M11: 50
A12: 11 | B12: 5 | C12: 120 | D12: 4 | E12: 5 | F12: 6 | G12: 4 | H12: 6 | I12: 7 | J12: 7 | K12: 5 | L12: 2 | M12: 45
A13: 12 | B13: 2 | C13: 520 | D13: 5 | E13: 7 | F13: 6 | G13: 2 | H13: 6 | I13: 5 | J13: 8 | K13: 8 | L13: 2 | M13: 65
... A36: 35 | B36: 2 | C36: 150 | D36: 4 | E36: 5 | F36: 6 | G36: 3 | H36: 4 | I36: 6 | J36: 7 | K36: 3 | L36: 1 | M36: 72

Sheet Normalized Data
A1: supplier | B1: quality | C1: quantity | D1: conditions and method of payment | E1: serviceability and communicativeness of the supplier | F1: reputation of the supplier and its competence | G1: flexibility | H1: financial condition of the supplier | I1: condition of the supplier's assets | J1: business results and number of employees | K1: price | L1: delivery time | M1: supplier's location and traffic connections
A2: ='Raw Data - Suppliers'!A2 -> 1 | B2: =('Raw Data - Suppliers'!B2-MIN('Raw Data - Suppliers'!B$2:B$36))/(MAX('Raw Data - Suppliers'!B$2:B$36)-MIN('Raw Data - Suppliers'!B$2:B$36)) -> 0.66666667 | C2: =('Raw Data - Suppliers'!C2-MIN('Raw Data - Suppliers'!C$2:C$36))/(MAX('Raw Data - Suppliers'!C$2:C$36)-MIN('Raw Data - Suppliers'!C$2:C$36)) -> 0.30666667 | D2: =('Raw Data - Suppliers'!D2-MIN('Raw Data - Suppliers'!D$2:D$36))/(MAX('Raw Data - Suppliers'!D$2:D$36)-MIN('Raw Data - Suppliers'!D$2:D$36)) -> 0.5 | E2: =('Raw Data - Suppliers'!E2-MIN('Raw Data - Suppliers'!E$2:E$36))/(MAX('Raw Data - Suppliers'!E$2:E$36)-MIN('Raw Data - Suppliers'!E$2:E$36)) -> 0 | F2: =('Raw Data - Suppliers'!F2-MIN('Raw Data - Suppliers'!F$2:F$36))/(MAX('Raw Data - Suppliers'!F$2:F$36)-MIN('Raw Data - Suppliers'!F$2:F$36)) -> 0 | G2: =('Raw Data - Suppliers'!G2-MIN('Raw Data - Suppliers'!G$2:G$36))/(MAX('Raw Data - Suppliers'!G$2:G$36)-MIN('Raw Data - Suppliers'!G$2:G$36)) -> 0.66666667 | H2: =('Raw Data - Suppliers'!H2-MIN('Raw Data - Suppliers'!H$2:H$36))/(MAX('Raw Data - Suppliers'!H$2:H$36)-MIN('Raw Data - Suppliers'!H$2:H$36)) -> 0.16666667 | I2: =('Raw Data - Suppliers'!I2-MIN('Raw Data - Suppliers'!I$2:I$36))/(MAX('Raw Data - Suppliers'!I$2:I$36)-MIN('Raw Data - Suppliers'!I$2:I$36)) -> 0 | J2: =('Raw Data - Suppliers'!J2-MIN('Raw Data - Suppliers'!J$2:J$36))/(MAX('Raw Data - Suppliers'!J$2:J$36)-MIN('Raw Data - Suppliers'!J$2:J$36)) -> 0.2 | K2: =1-('Raw Data - Suppliers'!K2-MIN('Raw Data - Suppliers'!K$2:K$36))/(MAX('Raw Data - Suppliers'!K$2:K$36)-MIN('Raw Data - Suppliers'!K$2:K$36)) -> 0.6 | L2: =('Raw Data - Suppliers'!L2-MIN('Raw Data - Suppliers'!L$2:L$36))/(MAX('Raw Data - Suppliers'!L$2:L$36)-MIN('Raw Data - Suppliers'!L$2:L$36)) -> 0.33333333 | M2: =1-('Raw Data - Suppliers'!M2-MIN('Raw Data - Suppliers'!M$2:M$36))/(MAX('Raw Data - Suppliers'!M$2:M$36)-MIN('Raw Data - Suppliers'!M$2:M$36)) -> 0.82926829
A3: ='Raw Data - Suppliers'!A3 -> 2 | B3: =('Raw Data - Suppliers'!B3-MIN('Raw Data - Suppliers'!B$2:B$36))/(MAX('Raw Data - Suppliers'!B$2:B$36)-MIN('Raw Data - Suppliers'!B$2:B$36)) -> 0 | C3: =('Raw Data - Suppliers'!C3-MIN('Raw Data - Suppliers'!C$2:C$36))/(MAX('Raw Data - Suppliers'!C$2:C$36)-MIN('Raw Data - Suppliers'!C$2:C$36)) -> 0.30666667 | D3: =('Raw Data - Suppliers'!D3-MIN('Raw Data - Suppliers'!D$2:D$36))/(MAX('Raw Data - Suppliers'!D$2:D$36)-MIN('Raw Data - Suppliers'!D$2:D$36)) -> 0.25 | E3: =('Raw Data - Suppliers'!E3-MIN('Raw Data - Suppliers'!E$2:E$36))/(MAX('Raw Data - Suppliers'!E$2:E$36)-MIN('Raw Data - Suppliers'!E$2:E$36)) -> 0.33333333 | F3: =('Raw Data - Suppliers'!F3-MIN('Raw Data - Suppliers'!F$2:F$36))/(MAX('Raw Data - Suppliers'!F$2:F$36)-MIN('Raw Data - Suppliers'!F$2:F$36)) -> 0 | G3: =('Raw Data - Suppliers'!G3-MIN('Raw Data - Suppliers'!G$2:G$36))/(MAX('Raw Data - Suppliers'!G$2:G$36)-MIN('Raw Data - Suppliers'!G$2:G$36)) -> 0.33333333 | H3: =('Raw Data - Suppliers'!H3-MIN('Raw Data - Suppliers'!H$2:H$36))/(MAX('Raw Data - Suppliers'!H$2:H$36)-MIN('Raw Data - Suppliers'!H$2:H$36)) -> 0.33333333 | I3: =('Raw Data - Suppliers'!I3-MIN('Raw Data - Suppliers'!I$2:I$36))/(MAX('Raw Data - Suppliers'!I$2:I$36)-MIN('Raw Data - Suppliers'!I$2:I$36)) -> 0.2 | J3: =('Raw Data - Suppliers'!J3-MIN('Raw Data - Suppliers'!J$2:J$36))/(MAX('Raw Data - Suppliers'!J$2:J$36)-MIN('Raw Data - Suppliers'!J$2:J$36)) -> 0.4 | K3: =1-('Raw Data - Suppliers'!K3-MIN('Raw Data - Suppliers'!K$2:K$36))/(MAX('Raw Data - Suppliers'!K$2:K$36)-MIN('Raw Data - Suppliers'!K$2:K$36)) -> 0.2 | L3: =('Raw Data - Suppliers'!L3-MIN('Raw Data - Suppliers'!L$2:L$36))/(MAX('Raw Data - Suppliers'!L$2:L$36)-MIN('Raw Data - Suppliers'!L$2:L$36)) -> 0.55555556 | M3: =1-('Raw Data - Suppliers'!M3-MIN('Raw Data - Suppliers'!M$2:M$36))/(MAX('Raw Data - Suppliers'!M$2:M$36)-MIN('Raw Data - Suppliers'!M$2:M$36)) -> 0.7804878
A4: ='Raw Data - Suppliers'!A4 -> 3 | B4: =('Raw Data - Suppliers'!B4-MIN('Raw Data - Suppliers'!B$2:B$36))/(MAX('Raw Data - Suppliers'!B$2:B$36)-MIN('Raw Data - Suppliers'!B$2:B$36)) -> 0 | C4: =('Raw Data - Suppliers'!C4-MIN('Raw Data - Suppliers'!C$2:C$36))/(MAX('Raw Data - Suppliers'!C$2:C$36)-MIN('Raw Data - Suppliers'!C$2:C$36)) -> 0.44 | D4: =('Raw Data - Suppliers'!D4-MIN('Raw Data - Suppliers'!D$2:D$36))/(MAX('Raw Data - Suppliers'!D$2:D$36)-MIN('Raw Data - Suppliers'!D$2:D$36)) -> 0.5 | E4: =('Raw Data - Suppliers'!E4-MIN('Raw Data - Suppliers'!E$2:E$36))/(MAX('Raw Data - Suppliers'!E$2:E$36)-MIN('Raw Data - Suppliers'!E$2:E$36)) -> 0.5 | F4: =('Raw Data - Suppliers'!F4-MIN('Raw Data - Suppliers'!F$2:F$36))/(MAX('Raw Data - Suppliers'!F$2:F$36)-MIN('Raw Data - Suppliers'!F$2:F$36)) -> 0.2 | G4: =('Raw Data - Suppliers'!G4-MIN('Raw Data - Suppliers'!G$2:G$36))/(MAX('Raw Data - Suppliers'!G$2:G$36)-MIN('Raw Data - Suppliers'!G$2:G$36)) -> 0.66666667 | H4: =('Raw Data - Suppliers'!H4-MIN('Raw Data - Suppliers'!H$2:H$36))/(MAX('Raw Data - Suppliers'!H$2:H$36)-MIN('Raw Data - Suppliers'!H$2:H$36)) -> 0.66666667 | I4: =('Raw Data - Suppliers'!I4-MIN('Raw Data - Suppliers'!I$2:I$36))/(MAX('Raw Data - Suppliers'!I$2:I$36)-MIN('Raw Data - Suppliers'!I$2:I$36)) -> 1 | J4: =('Raw Data - Suppliers'!J4-MIN('Raw Data - Suppliers'!J$2:J$36))/(MAX('Raw Data - Suppliers'!J$2:J$36)-MIN('Raw Data - Suppliers'!J$2:J$36)) -> 1 | K4: =1-('Raw Data - Suppliers'!K4-MIN('Raw Data - Suppliers'!K$2:K$36))/(MAX('Raw Data - Suppliers'!K$2:K$36)-MIN('Raw Data - Suppliers'!K$2:K$36)) -> 0 | L4: =('Raw Data - Suppliers'!L4-MIN('Raw Data - Suppliers'!L$2:L$36))/(MAX('Raw Data - Suppliers'!L$2:L$36)-MIN('Raw Data - Suppliers'!L$2:L$36)) -> 0.77777778 | M4: =1-('Raw Data - Suppliers'!M4-MIN('Raw Data - Suppliers'!M$2:M$36))/(MAX('Raw Data - Suppliers'!M$2:M$36)-MIN('Raw Data - Suppliers'!M$2:M$36)) -> 0.92682927
A5: ='Raw Data - Suppliers'!A5 -> 4 | B5: =('Raw Data - Suppliers'!B5-MIN('Raw Data - Suppliers'!B$2:B$36))/(MAX('Raw Data - Suppliers'!B$2:B$36)-MIN('Raw Data - Suppliers'!B$2:B$36)) -> 0.66666667 | C5: =('Raw Data - Suppliers'!C5-MIN('Raw Data - Suppliers'!C$2:C$36))/(MAX('Raw Data - Suppliers'!C$2:C$36)-MIN('Raw Data - Suppliers'!C$2:C$36)) -> 0.18666667 | D5: =('Raw Data - Suppliers'!D5-MIN('Raw Data - Suppliers'!D$2:D$36))/(MAX('Raw Data - Suppliers'!D$2:D$36)-MIN('Raw Data - Suppliers'!D$2:D$36)) -> 0.5 | E5: =('Raw Data - Suppliers'!E5-MIN('Raw Data - Suppliers'!E$2:E$36))/(MAX('Raw Data - Suppliers'!E$2:E$36)-MIN('Raw Data - Suppliers'!E$2:E$36)) -> 0.5 | F5: =('Raw Data - Suppliers'!F5-MIN('Raw Data - Suppliers'!F$2:F$36))/(MAX('Raw Data - Suppliers'!F$2:F$36)-MIN('Raw Data - Suppliers'!F$2:F$36)) -> 0.8 | G5: =('Raw Data - Suppliers'!G5-MIN('Raw Data - Suppliers'!G$2:G$36))/(MAX('Raw Data - Suppliers'!G$2:G$36)-MIN('Raw Data - Suppliers'!G$2:G$36)) -> 1 | H5: =('Raw Data - Suppliers'!H5-MIN('Raw Data - Suppliers'!H$2:H$36))/(MAX('Raw Data - Suppliers'!H$2:H$36)-MIN('Raw Data - Suppliers'!H$2:H$36)) -> 0.66666667 | I5: =('Raw Data - Suppliers'!I5-MIN('Raw Data - Suppliers'!I$2:I$36))/(MAX('Raw Data - Suppliers'!I$2:I$36)-MIN('Raw Data - Suppliers'!I$2:I$36)) -> 1 | J5: =('Raw Data - Suppliers'!J5-MIN('Raw Data - Suppliers'!J$2:J$36))/(MAX('Raw Data - Suppliers'!J$2:J$36)-MIN('Raw Data - Suppliers'!J$2:J$36)) -> 1 | K5: =1-('Raw Data - Suppliers'!K5-MIN('Raw Data - Suppliers'!K$2:K$36))/(MAX('Raw Data - Suppliers'!K$2:K$36)-MIN('Raw Data - Suppliers'!K$2:K$36)) -> 0.2 | L5: =('Raw Data - Suppliers'!L5-MIN('Raw Data - Suppliers'!L$2:L$36))/(MAX('Raw Data - Suppliers'!L$2:L$36)-MIN('Raw Data - Suppliers'!L$2:L$36)) -> 0.11111111 | M5: =1-('Raw Data - Suppliers'!M5-MIN('Raw Data - Suppliers'!M$2:M$36))/(MAX('Raw Data - Suppliers'!M$2:M$36)-MIN('Raw Data - Suppliers'!M$2:M$36)) -> 0.87804878
A6: ='Raw Data - Suppliers'!A6 -> 5 | B6: =('Raw Data - Suppliers'!B6-MIN('Raw Data - Suppliers'!B$2:B$36))/(MAX('Raw Data - Suppliers'!B$2:B$36)-MIN('Raw Data - Suppliers'!B$2:B$36)) -> 0.33333333 | C6: =('Raw Data - Suppliers'!C6-MIN('Raw Data - Suppliers'!C$2:C$36))/(MAX('Raw Data - Suppliers'!C$2:C$36)-MIN('Raw Data - Suppliers'!C$2:C$36)) -> 0.066666667 | D6: =('Raw Data - Suppliers'!D6-MIN('Raw Data - Suppliers'!D$2:D$36))/(MAX('Raw Data - Suppliers'!D$2:D$36)-MIN('Raw Data - Suppliers'!D$2:D$36)) -> 0.5 | E6: =('Raw Data - Suppliers'!E6-MIN('Raw Data - Suppliers'!E$2:E$36))/(MAX('Raw Data - Suppliers'!E$2:E$36)-MIN('Raw Data - Suppliers'!E$2:E$36)) -> 0.66666667 | F6: =('Raw Data - Suppliers'!F6-MIN('Raw Data - Suppliers'!F$2:F$36))/(MAX('Raw Data - Suppliers'!F$2:F$36)-MIN('Raw Data - Suppliers'!F$2:F$36)) -> 0.4 | G6: =('Raw Data - Suppliers'!G6-MIN('Raw Data - Suppliers'!G$2:G$36))/(MAX('Raw Data - Suppliers'!G$2:G$36)-MIN('Raw Data - Suppliers'!G$2:G$36)) -> 0 | H6: =('Raw Data - Suppliers'!H6-MIN('Raw Data - Suppliers'!H$2:H$36))/(MAX('Raw Data - Suppliers'!H$2:H$36)-MIN('Raw Data - Suppliers'!H$2:H$36)) -> 0.5 | I6: =('Raw Data - Suppliers'!I6-MIN('Raw Data - Suppliers'!I$2:I$36))/(MAX('Raw Data - Suppliers'!I$2:I$36)-MIN('Raw Data - Suppliers'!I$2:I$36)) -> 0.4 | J6: =('Raw Data - Suppliers'!J6-MIN('Raw Data - Suppliers'!J$2:J$36))/(MAX('Raw Data - Suppliers'!J$2:J$36)-MIN('Raw Data - Suppliers'!J$2:J$36)) -> 0 | K6: =1-('Raw Data - Suppliers'!K6-MIN('Raw Data - Suppliers'!K$2:K$36))/(MAX('Raw Data - Suppliers'!K$2:K$36)-MIN('Raw Data - Suppliers'!K$2:K$36)) -> 0.2 | L6: =('Raw Data - Suppliers'!L6-MIN('Raw Data - Suppliers'!L$2:L$36))/(MAX('Raw Data - Suppliers'!L$2:L$36)-MIN('Raw Data - Suppliers'!L$2:L$36)) -> 0.33333333 | M6: =1-('Raw Data - Suppliers'!M6-MIN('Raw Data - Suppliers'!M$2:M$36))/(MAX('Raw Data - Suppliers'!M$2:M$36)-MIN('Raw Data - Suppliers'!M$2:M$36)) -> 0.90243902
A7: ='Raw Data - Suppliers'!A7 -> 6 | B7: =('Raw Data - Suppliers'!B7-MIN('Raw Data - Suppliers'!B$2:B$36))/(MAX('Raw Data - Suppliers'!B$2:B$36)-MIN('Raw Data - Suppliers'!B$2:B$36)) -> 0.66666667 | C7: =('Raw Data - Suppliers'!C7-MIN('Raw Data - Suppliers'!C$2:C$36))/(MAX('Raw Data - Suppliers'!C$2:C$36)-MIN('Raw Data - Suppliers'!C$2:C$36)) -> 0.08 | D7: =('Raw Data - Suppliers'!D7-MIN('Raw Data - Suppliers'!D$2:D$36))/(MAX('Raw Data - Suppliers'!D$2:D$36)-MIN('Raw Data - Suppliers'!D$2:D$36)) -> 0 | E7: =('Raw Data - Suppliers'!E7-MIN('Raw Data - Suppliers'!E$2:E$36))/(MAX('Raw Data - Suppliers'!E$2:E$36)-MIN('Raw Data - Suppliers'!E$2:E$36)) -> 0.83333333 | F7: =('Raw Data - Suppliers'!F7-MIN('Raw Data - Suppliers'!F$2:F$36))/(MAX('Raw Data - Suppliers'!F$2:F$36)-MIN('Raw Data - Suppliers'!F$2:F$36)) -> 0.8 | G7: =('Raw Data - Suppliers'!G7-MIN('Raw Data - Suppliers'!G$2:G$36))/(MAX('Raw Data - Suppliers'!G$2:G$36)-MIN('Raw Data - Suppliers'!G$2:G$36)) -> 0 | H7: =('Raw Data - Suppliers'!H7-MIN('Raw Data - Suppliers'!H$2:H$36))/(MAX('Raw Data - Suppliers'!H$2:H$36)-MIN('Raw Data - Suppliers'!H$2:H$36)) -> 1 | I7: =('Raw Data - Suppliers'!I7-MIN('Raw Data - Suppliers'!I$2:I$36))/(MAX('Raw Data - Suppliers'!I$2:I$36)-MIN('Raw Data - Suppliers'!I$2:I$36)) -> 0.8 | J7: =('Raw Data - Suppliers'!J7-MIN('Raw Data - Suppliers'!J$2:J$36))/(MAX('Raw Data - Suppliers'!J$2:J$36)-MIN('Raw Data - Suppliers'!J$2:J$36)) -> 0.2 | K7: =1-('Raw Data - Suppliers'!K7-MIN('Raw Data - Suppliers'!K$2:K$36))/(MAX('Raw Data - Suppliers'!K$2:K$36)-MIN('Raw Data - Suppliers'!K$2:K$36)) -> 0 | L7: =('Raw Data - Suppliers'!L7-MIN('Raw Data - Suppliers'!L$2:L$36))/(MAX('Raw Data - Suppliers'!L$2:L$36)-MIN('Raw Data - Suppliers'!L$2:L$36)) -> 0 | M7: =1-('Raw Data - Suppliers'!M7-MIN('Raw Data - Suppliers'!M$2:M$36))/(MAX('Raw Data - Suppliers'!M$2:M$36)-MIN('Raw Data - Suppliers'!M$2:M$36)) -> 0.80487805
A8: ='Raw Data - Suppliers'!A8 -> 7 | B8: =('Raw Data - Suppliers'!B8-MIN('Raw Data - Suppliers'!B$2:B$36))/(MAX('Raw Data - Suppliers'!B$2:B$36)-MIN('Raw Data - Suppliers'!B$2:B$36)) -> 0.33333333 | C8: =('Raw Data - Suppliers'!C8-MIN('Raw Data - Suppliers'!C$2:C$36))/(MAX('Raw Data - Suppliers'!C$2:C$36)-MIN('Raw Data - Suppliers'!C$2:C$36)) -> 0.30666667 | D8: =('Raw Data - Suppliers'!D8-MIN('Raw Data - Suppliers'!D$2:D$36))/(MAX('Raw Data - Suppliers'!D$2:D$36)-MIN('Raw Data - Suppliers'!D$2:D$36)) -> 0 | E8: =('Raw Data - Suppliers'!E8-MIN('Raw Data - Suppliers'!E$2:E$36))/(MAX('Raw Data - Suppliers'!E$2:E$36)-MIN('Raw Data - Suppliers'!E$2:E$36)) -> 0 | F8: =('Raw Data - Suppliers'!F8-MIN('Raw Data - Suppliers'!F$2:F$36))/(MAX('Raw Data - Suppliers'!F$2:F$36)-MIN('Raw Data - Suppliers'!F$2:F$36)) -> 0 | G8: =('Raw Data - Suppliers'!G8-MIN('Raw Data - Suppliers'!G$2:G$36))/(MAX('Raw Data - Suppliers'!G$2:G$36)-MIN('Raw Data - Suppliers'!G$2:G$36)) -> 0.66666667 | H8: =('Raw Data - Suppliers'!H8-MIN('Raw Data - Suppliers'!H$2:H$36))/(MAX('Raw Data - Suppliers'!H$2:H$36)-MIN('Raw Data - Suppliers'!H$2:H$36)) -> 0.16666667 | I8: =('Raw Data - Suppliers'!I8-MIN('Raw Data - Suppliers'!I$2:I$36))/(MAX('Raw Data - Suppliers'!I$2:I$36)-MIN('Raw Data - Suppliers'!I$2:I$36)) -> 0 | J8: =('Raw Data - Suppliers'!J8-MIN('Raw Data - Suppliers'!J$2:J$36))/(MAX('Raw Data - Suppliers'!J$2:J$36)-MIN('Raw Data - Suppliers'!J$2:J$36)) -> 0.2 | K8: =1-('Raw Data - Suppliers'!K8-MIN('Raw Data - Suppliers'!K$2:K$36))/(MAX('Raw Data - Suppliers'!K$2:K$36)-MIN('Raw Data - Suppliers'!K$2:K$36)) -> 0.6 | L8: =('Raw Data - Suppliers'!L8-MIN('Raw Data - Suppliers'!L$2:L$36))/(MAX('Raw Data - Suppliers'!L$2:L$36)-MIN('Raw Data - Suppliers'!L$2:L$36)) -> 0.33333333 | M8: =1-('Raw Data - Suppliers'!M8-MIN('Raw Data - Suppliers'!M$2:M$36))/(MAX('Raw Data - Suppliers'!M$2:M$36)-MIN('Raw Data - Suppliers'!M$2:M$36)) -> 0.77073171
A9: ='Raw Data - Suppliers'!A9 -> 8 | B9: =('Raw Data - Suppliers'!B9-MIN('Raw Data - Suppliers'!B$2:B$36))/(MAX('Raw Data - Suppliers'!B$2:B$36)-MIN('Raw Data - Suppliers'!B$2:B$36)) -> 0.33333333 | C9: =('Raw Data - Suppliers'!C9-MIN('Raw Data - Suppliers'!C$2:C$36))/(MAX('Raw Data - Suppliers'!C$2:C$36)-MIN('Raw Data - Suppliers'!C$2:C$36)) -> 0.17333333 | D9: =('Raw Data - Suppliers'!D9-MIN('Raw Data - Suppliers'!D$2:D$36))/(MAX('Raw Data - Suppliers'!D$2:D$36)-MIN('Raw Data - Suppliers'!D$2:D$36)) -> 0 | E9: =('Raw Data - Suppliers'!E9-MIN('Raw Data - Suppliers'!E$2:E$36))/(MAX('Raw Data - Suppliers'!E$2:E$36)-MIN('Raw Data - Suppliers'!E$2:E$36)) -> 0.5 | F9: =('Raw Data - Suppliers'!F9-MIN('Raw Data - Suppliers'!F$2:F$36))/(MAX('Raw Data - Suppliers'!F$2:F$36)-MIN('Raw Data - Suppliers'!F$2:F$36)) -> 0.2 | G9: =('Raw Data - Suppliers'!G9-MIN('Raw Data - Suppliers'!G$2:G$36))/(MAX('Raw Data - Suppliers'!G$2:G$36)-MIN('Raw Data - Suppliers'!G$2:G$36)) -> 0.33333333 | H9: =('Raw Data - Suppliers'!H9-MIN('Raw Data - Suppliers'!H$2:H$36))/(MAX('Raw Data - Suppliers'!H$2:H$36)-MIN('Raw Data - Suppliers'!H$2:H$36)) -> 0.5 | I9: =('Raw Data - Suppliers'!I9-MIN('Raw Data - Suppliers'!I$2:I$36))/(MAX('Raw Data - Suppliers'!I$2:I$36)-MIN('Raw Data - Suppliers'!I$2:I$36)) -> 0.4 | J9: =('Raw Data - Suppliers'!J9-MIN('Raw Data - Suppliers'!J$2:J$36))/(MAX('Raw Data - Suppliers'!J$2:J$36)-MIN('Raw Data - Suppliers'!J$2:J$36)) -> 0 | K9: =1-('Raw Data - Suppliers'!K9-MIN('Raw Data - Suppliers'!K$2:K$36))/(MAX('Raw Data - Suppliers'!K$2:K$36)-MIN('Raw Data - Suppliers'!K$2:K$36)) -> 0.4 | L9: =('Raw Data - Suppliers'!L9-MIN('Raw Data - Suppliers'!L$2:L$36))/(MAX('Raw Data - Suppliers'!L$2:L$36)-MIN('Raw Data - Suppliers'!L$2:L$36)) -> 0.77777778 | M9: =1-('Raw Data - Suppliers'!M9-MIN('Raw Data - Suppliers'!M$2:M$36))/(MAX('Raw Data - Suppliers'!M$2:M$36)-MIN('Raw Data - Suppliers'!M$2:M$36)) -> 0.69268293
A10: ='Raw Data - Suppliers'!A10 -> 9 | B10: =('Raw Data - Suppliers'!B10-MIN('Raw Data - Suppliers'!B$2:B$36))/(MAX('Raw Data - Suppliers'!B$2:B$36)-MIN('Raw Data - Suppliers'!B$2:B$36)) -> 1 | C10: =('Raw Data - Suppliers'!C10-MIN('Raw Data - Suppliers'!C$2:C$36))/(MAX('Raw Data - Suppliers'!C$2:C$36)-MIN('Raw Data - Suppliers'!C$2:C$36)) -> 0.32 | D10: =('Raw Data - Suppliers'!D10-MIN('Raw Data - Suppliers'!D$2:D$36))/(MAX('Raw Data - Suppliers'!D$2:D$36)-MIN('Raw Data - Suppliers'!D$2:D$36)) -> 0.75 | E10: =('Raw Data - Suppliers'!E10-MIN('Raw Data - Suppliers'!E$2:E$36))/(MAX('Raw Data - Suppliers'!E$2:E$36)-MIN('Raw Data - Suppliers'!E$2:E$36)) -> 1 | F10: =('Raw Data - Suppliers'!F10-MIN('Raw Data - Suppliers'!F$2:F$36))/(MAX('Raw Data - Suppliers'!F$2:F$36)-MIN('Raw Data - Suppliers'!F$2:F$36)) -> 0.8 | G10: =('Raw Data - Suppliers'!G10-MIN('Raw Data - Suppliers'!G$2:G$36))/(MAX('Raw Data - Suppliers'!G$2:G$36)-MIN('Raw Data - Suppliers'!G$2:G$36)) -> 1 | H10: =('Raw Data - Suppliers'!H10-MIN('Raw Data - Suppliers'!H$2:H$36))/(MAX('Raw Data - Suppliers'!H$2:H$36)-MIN('Raw Data - Suppliers'!H$2:H$36)) -> 0.83333333 | I10: =('Raw Data - Suppliers'!I10-MIN('Raw Data - Suppliers'!I$2:I$36))/(MAX('Raw Data - Suppliers'!I$2:I$36)-MIN('Raw Data - Suppliers'!I$2:I$36)) -> 0.6 | J10: =('Raw Data - Suppliers'!J10-MIN('Raw Data - Suppliers'!J$2:J$36))/(MAX('Raw Data - Suppliers'!J$2:J$36)-MIN('Raw Data - Suppliers'!J$2:J$36)) -> 0.2 | K10: =1-('Raw Data - Suppliers'!K10-MIN('Raw Data - Suppliers'!K$2:K$36))/(MAX('Raw Data - Suppliers'!K$2:K$36)-MIN('Raw Data - Suppliers'!K$2:K$36)) -> 0.4 | L10: =('Raw Data - Suppliers'!L10-MIN('Raw Data - Suppliers'!L$2:L$36))/(MAX('Raw Data - Suppliers'!L$2:L$36)-MIN('Raw Data - Suppliers'!L$2:L$36)) -> 0.55555556 | M10: =1-('Raw Data - Suppliers'!M10-MIN('Raw Data - Suppliers'!M$2:M$36))/(MAX('Raw Data - Suppliers'!M$2:M$36)-MIN('Raw Data - Suppliers'!M$2:M$36)) -> 0.48780488
A11: ='Raw Data - Suppliers'!A11 -> 10 | B11: =('Raw Data - Suppliers'!B11-MIN('Raw Data - Suppliers'!B$2:B$36))/(MAX('Raw Data - Suppliers'!B$2:B$36)-MIN('Raw Data - Suppliers'!B$2:B$36)) -> 0.66666667 | C11: =('Raw Data - Suppliers'!C11-MIN('Raw Data - Suppliers'!C$2:C$36))/(MAX('Raw Data - Suppliers'!C$2:C$36)-MIN('Raw Data - Suppliers'!C$2:C$36)) -> 0.16 | D11: =('Raw Data - Suppliers'!D11-MIN('Raw Data - Suppliers'!D$2:D$36))/(MAX('Raw Data - Suppliers'!D$2:D$36)-MIN('Raw Data - Suppliers'!D$2:D$36)) -> 0.75 | E11: =('Raw Data - Suppliers'!E11-MIN('Raw Data - Suppliers'!E$2:E$36))/(MAX('Raw Data - Suppliers'!E$2:E$36)-MIN('Raw Data - Suppliers'!E$2:E$36)) -> 1 | F11: =('Raw Data - Suppliers'!F11-MIN('Raw Data - Suppliers'!F$2:F$36))/(MAX('Raw Data - Suppliers'!F$2:F$36)-MIN('Raw Data - Suppliers'!F$2:F$36)) -> 0.8 | G11: =('Raw Data - Suppliers'!G11-MIN('Raw Data - Suppliers'!G$2:G$36))/(MAX('Raw Data - Suppliers'!G$2:G$36)-MIN('Raw Data - Suppliers'!G$2:G$36)) -> 0.33333333 | H11: =('Raw Data - Suppliers'!H11-MIN('Raw Data - Suppliers'!H$2:H$36))/(MAX('Raw Data - Suppliers'!H$2:H$36)-MIN('Raw Data - Suppliers'!H$2:H$36)) -> 0.83333333 | I11: =('Raw Data - Suppliers'!I11-MIN('Raw Data - Suppliers'!I$2:I$36))/(MAX('Raw Data - Suppliers'!I$2:I$36)-MIN('Raw Data - Suppliers'!I$2:I$36)) -> 0.6 | J11: =('Raw Data - Suppliers'!J11-MIN('Raw Data - Suppliers'!J$2:J$36))/(MAX('Raw Data - Suppliers'!J$2:J$36)-MIN('Raw Data - Suppliers'!J$2:J$36)) -> 0.4 | K11: =1-('Raw Data - Suppliers'!K11-MIN('Raw Data - Suppliers'!K$2:K$36))/(MAX('Raw Data - Suppliers'!K$2:K$36)-MIN('Raw Data - Suppliers'!K$2:K$36)) -> 0.2 | L11: =('Raw Data - Suppliers'!L11-MIN('Raw Data - Suppliers'!L$2:L$36))/(MAX('Raw Data - Suppliers'!L$2:L$36)-MIN('Raw Data - Suppliers'!L$2:L$36)) -> 0.11111111 | M11: =1-('Raw Data - Suppliers'!M11-MIN('Raw Data - Suppliers'!M$2:M$36))/(MAX('Raw Data - Suppliers'!M$2:M$36)-MIN('Raw Data - Suppliers'!M$2:M$36)) -> 0.82926829
A12: ='Raw Data - Suppliers'!A12 -> 11 | B12: =('Raw Data - Suppliers'!B12-MIN('Raw Data - Suppliers'!B$2:B$36))/(MAX('Raw Data - Suppliers'!B$2:B$36)-MIN('Raw Data - Suppliers'!B$2:B$36)) -> 1 | C12: =('Raw Data - Suppliers'!C12-MIN('Raw Data - Suppliers'!C$2:C$36))/(MAX('Raw Data - Suppliers'!C$2:C$36)-MIN('Raw Data - Suppliers'!C$2:C$36)) -> 0 | D12: =('Raw Data - Suppliers'!D12-MIN('Raw Data - Suppliers'!D$2:D$36))/(MAX('Raw Data - Suppliers'!D$2:D$36)-MIN('Raw Data - Suppliers'!D$2:D$36)) -> 0.75 | E12: =('Raw Data - Suppliers'!E12-MIN('Raw Data - Suppliers'!E$2:E$36))/(MAX('Raw Data - Suppliers'!E$2:E$36)-MIN('Raw Data - Suppliers'!E$2:E$36)) -> 0.33333333 | F12: =('Raw Data - Suppliers'!F12-MIN('Raw Data - Suppliers'!F$2:F$36))/(MAX('Raw Data - Suppliers'!F$2:F$36)-MIN('Raw Data - Suppliers'!F$2:F$36)) -> 0.4 | G12: =('Raw Data - Suppliers'!G12-MIN('Raw Data - Suppliers'!G$2:G$36))/(MAX('Raw Data - Suppliers'!G$2:G$36)-MIN('Raw Data - Suppliers'!G$2:G$36)) -> 0.66666667 | H12: =('Raw Data - Suppliers'!H12-MIN('Raw Data - Suppliers'!H$2:H$36))/(MAX('Raw Data - Suppliers'!H$2:H$36)-MIN('Raw Data - Suppliers'!H$2:H$36)) -> 0.5 | I12: =('Raw Data - Suppliers'!I12-MIN('Raw Data - Suppliers'!I$2:I$36))/(MAX('Raw Data - Suppliers'!I$2:I$36)-MIN('Raw Data - Suppliers'!I$2:I$36)) -> 0.8 | J12: =('Raw Data - Suppliers'!J12-MIN('Raw Data - Suppliers'!J$2:J$36))/(MAX('Raw Data - Suppliers'!J$2:J$36)-MIN('Raw Data - Suppliers'!J$2:J$36)) -> 0.6 | K12: =1-('Raw Data - Suppliers'!K12-MIN('Raw Data - Suppliers'!K$2:K$36))/(MAX('Raw Data - Suppliers'!K$2:K$36)-MIN('Raw Data - Suppliers'!K$2:K$36)) -> 0.6 | L12: =('Raw Data - Suppliers'!L12-MIN('Raw Data - Suppliers'!L$2:L$36))/(MAX('Raw Data - Suppliers'!L$2:L$36)-MIN('Raw Data - Suppliers'!L$2:L$36)) -> 0.33333333 | M12: =1-('Raw Data - Suppliers'!M12-MIN('Raw Data - Suppliers'!M$2:M$36))/(MAX('Raw Data - Suppliers'!M$2:M$36)-MIN('Raw Data - Suppliers'!M$2:M$36)) -> 0.85365854
A13: ='Raw Data - Suppliers'!A13 -> 12 | B13: =('Raw Data - Suppliers'!B13-MIN('Raw Data - Suppliers'!B$2:B$36))/(MAX('Raw Data - Suppliers'!B$2:B$36)-MIN('Raw Data - Suppliers'!B$2:B$36)) -> 0 | C13: =('Raw Data - Suppliers'!C13-MIN('Raw Data - Suppliers'!C$2:C$36))/(MAX('Raw Data - Suppliers'!C$2:C$36)-MIN('Raw Data - Suppliers'!C$2:C$36)) -> 0.53333333 | D13: =('Raw Data - Suppliers'!D13-MIN('Raw Data - Suppliers'!D$2:D$36))/(MAX('Raw Data - Suppliers'!D$2:D$36)-MIN('Raw Data - Suppliers'!D$2:D$36)) -> 1 | E13: =('Raw Data - Suppliers'!E13-MIN('Raw Data - Suppliers'!E$2:E$36))/(MAX('Raw Data - Suppliers'!E$2:E$36)-MIN('Raw Data - Suppliers'!E$2:E$36)) -> 0.66666667 | F13: =('Raw Data - Suppliers'!F13-MIN('Raw Data - Suppliers'!F$2:F$36))/(MAX('Raw Data - Suppliers'!F$2:F$36)-MIN('Raw Data - Suppliers'!F$2:F$36)) -> 0.4 | G13: =('Raw Data - Suppliers'!G13-MIN('Raw Data - Suppliers'!G$2:G$36))/(MAX('Raw Data - Suppliers'!G$2:G$36)-MIN('Raw Data - Suppliers'!G$2:G$36)) -> 0 | H13: =('Raw Data - Suppliers'!H13-MIN('Raw Data - Suppliers'!H$2:H$36))/(MAX('Raw Data - Suppliers'!H$2:H$36)-MIN('Raw Data - Suppliers'!H$2:H$36)) -> 0.5 | I13: =('Raw Data - Suppliers'!I13-MIN('Raw Data - Suppliers'!I$2:I$36))/(MAX('Raw Data - Suppliers'!I$2:I$36)-MIN('Raw Data - Suppliers'!I$2:I$36)) -> 0.4 | J13: =('Raw Data - Suppliers'!J13-MIN('Raw Data - Suppliers'!J$2:J$36))/(MAX('Raw Data - Suppliers'!J$2:J$36)-MIN('Raw Data - Suppliers'!J$2:J$36)) -> 0.8 | K13: =1-('Raw Data - Suppliers'!K13-MIN('Raw Data - Suppliers'!K$2:K$36))/(MAX('Raw Data - Suppliers'!K$2:K$36)-MIN('Raw Data - Suppliers'!K$2:K$36)) -> 0 | L13: =('Raw Data - Suppliers'!L13-MIN('Raw Data - Suppliers'!L$2:L$36))/(MAX('Raw Data - Suppliers'!L$2:L$36)-MIN('Raw Data - Suppliers'!L$2:L$36)) -> 0.33333333 | M13: =1-('Raw Data - Suppliers'!M13-MIN('Raw Data - Suppliers'!M$2:M$36))/(MAX('Raw Data - Suppliers'!M$2:M$36)-MIN('Raw Data - Suppliers'!M$2:M$36)) -> 0.75609756
... A36: ='Raw Data - Suppliers'!A36 -> 35 | B36: =('Raw Data - Suppliers'!B36-MIN('Raw Data - Suppliers'!B$2:B$36))/(MAX('Raw Data - Suppliers'!B$2:B$36)-MIN('Raw Data - Suppliers'!B$2:B$36)) -> 0 | C36: =('Raw Data - Suppliers'!C36-MIN('Raw Data - Suppliers'!C$2:C$36))/(MAX('Raw Data - Suppliers'!C$2:C$36)-MIN('Raw Data - Suppliers'!C$2:C$36)) -> 0.04 | D36: =('Raw Data - Suppliers'!D36-MIN('Raw Data - Suppliers'!D$2:D$36))/(MAX('Raw Data - Suppliers'!D$2:D$36)-MIN('Raw Data - Suppliers'!D$2:D$36)) -> 0.75 | E36: =('Raw Data - Suppliers'!E36-MIN('Raw Data - Suppliers'!E$2:E$36))/(MAX('Raw Data - Suppliers'!E$2:E$36)-MIN('Raw Data - Suppliers'!E$2:E$36)) -> 0.33333333 | F36: =('Raw Data - Suppliers'!F36-MIN('Raw Data - Suppliers'!F$2:F$36))/(MAX('Raw Data - Suppliers'!F$2:F$36)-MIN('Raw Data - Suppliers'!F$2:F$36)) -> 0.4 | G36: =('Raw Data - Suppliers'!G36-MIN('Raw Data - Suppliers'!G$2:G$36))/(MAX('Raw Data - Suppliers'!G$2:G$36)-MIN('Raw Data - Suppliers'!G$2:G$36)) -> 0.33333333 | H36: =('Raw Data - Suppliers'!H36-MIN('Raw Data - Suppliers'!H$2:H$36))/(MAX('Raw Data - Suppliers'!H$2:H$36)-MIN('Raw Data - Suppliers'!H$2:H$36)) -> 0.16666667 | I36: =('Raw Data - Suppliers'!I36-MIN('Raw Data - Suppliers'!I$2:I$36))/(MAX('Raw Data - Suppliers'!I$2:I$36)-MIN('Raw Data - Suppliers'!I$2:I$36)) -> 0.6 | J36: =('Raw Data - Suppliers'!J36-MIN('Raw Data - Suppliers'!J$2:J$36))/(MAX('Raw Data - Suppliers'!J$2:J$36)-MIN('Raw Data - Suppliers'!J$2:J$36)) -> 0.6 | K36: =1-('Raw Data - Suppliers'!K36-MIN('Raw Data - Suppliers'!K$2:K$36))/(MAX('Raw Data - Suppliers'!K$2:K$36)-MIN('Raw Data - Suppliers'!K$2:K$36)) -> 1 | L36: =('Raw Data - Suppliers'!L36-MIN('Raw Data - Suppliers'!L$2:L$36))/(MAX('Raw Data - Suppliers'!L$2:L$36)-MIN('Raw Data - Suppliers'!L$2:L$36)) -> 0.11111111 | M36: =1-('Raw Data - Suppliers'!M36-MIN('Raw Data - Suppliers'!M$2:M$36))/(MAX('Raw Data - Suppliers'!M$2:M$36)-MIN('Raw Data - Suppliers'!M$2:M$36)) -> 0.72195122

Sheet Weights
A1: Criteria | B1: Weight | C1: Justification
A2: quality | B2: 0.15 | C2: Product conformance
A3: quantity | B3: 0.05 | C3: Supply capacity
A4: conditions and method of payment | B4: 0.08 | C4: Cash flow impact
A5: serviceability and communicativeness | B5: 0.08 | C5: Operational support
A6: reputation and competence | B6: 0.1 | C6: Long-term reliability
A7: flexibility | B7: 0.08 | C7: Supply chain resilience
A8: financial condition | B8: 0.08 | C8: Supplier stability
A9: condition of assets | B9: 0.05 | C9: Production capability
A10: business results and employees | B10: 0.05 | C10: Supplier health
A11: price | B11: 0.15 | C11: Direct cost impact
A12: delivery time | B12: 0.12 | C12: Operational continuity
A13: location and traffic | B13: 0.01 | C13: Logistics cost
B14: =SUM(B2:B13) -> 1

Sheet Scoring
A1: Supplier ID | B1: Weighted Score | C1: Rank | D1: Classification | E1: Best Criteria Score | F1: Worst Criteria Score | G1: Best Criteria Name | H1: Worst Criteria Name
A2: ='Normalized Data'!A10 -> 9 | B2: {=SUMPRODUCT('Normalized Data'!B10:M10,TRANSPOSE(Weights!$B$2:$B$13))} -> 0.70421138 | C2: =RANK(B2,$B$2:$B$36,0) -> 1 | D2: =IF(C2<=7,"Preferred",IF(C2<=21,"Approved","Conditional")) -> Preferred | E2: =MAX('Normalized Data'!B10:M10) -> 1 | F2: =MIN('Normalized Data'!B10:M10) -> 0.2 | G2: =INDEX(Weights!$A$2:$A$13,MATCH(MAX('Normalized Data'!B10:M10),'Normalized Data'!B10:M10,0)) -> quality | H2: =INDEX(Weights!$A$2:$A$13,MATCH(MIN('Normalized Data'!B10:M10),'Normalized Data'!B10:M10,0)) -> business results and employees
A3: ='Normalized Data'!A25 -> 24 | B3: {=SUMPRODUCT('Normalized Data'!B25:M25,TRANSPOSE(Weights!$B$2:$B$13))} -> 0.68053659 | C3: =RANK(B3,$B$2:$B$36,0) -> 2 | D3: =IF(C3<=7,"Preferred",IF(C3<=21,"Approved","Conditional")) -> Preferred | E3: =MAX('Normalized Data'!B25:M25) -> 1 | F3: =MIN('Normalized Data'!B25:M25) -> 0.30666667 | G3: =INDEX(Weights!$A$2:$A$13,MATCH(MAX('Normalized Data'!B25:M25),'Normalized Data'!B25:M25,0)) -> reputation and competence | H3: =INDEX(Weights!$A$2:$A$13,MATCH(MIN('Normalized Data'!B25:M25),'Normalized Data'!B25:M25,0)) -> quantity
A4: ='Normalized Data'!A15 -> 14 | B4: {=SUMPRODUCT('Normalized Data'!B15:M15,TRANSPOSE(Weights!$B$2:$B$13))} -> 0.65834146 | C4: =RANK(B4,$B$2:$B$36,0) -> 3 | D4: =IF(C4<=7,"Preferred",IF(C4<=21,"Approved","Conditional")) -> Preferred | E4: =MAX('Normalized Data'!B15:M15) -> 1 | F4: =MIN('Normalized Data'!B15:M15) -> 0.44 | G4: =INDEX(Weights!$A$2:$A$13,MATCH(MAX('Normalized Data'!B15:M15),'Normalized Data'!B15:M15,0)) -> conditions and method of payment | H4: =INDEX(Weights!$A$2:$A$13,MATCH(MIN('Normalized Data'!B15:M15),'Normalized Data'!B15:M15,0)) -> quantity
A5: ='Normalized Data'!A28 -> 27 | B5: {=SUMPRODUCT('Normalized Data'!B28:M28,TRANSPOSE(Weights!$B$2:$B$13))} -> 0.62347967 | C5: =RANK(B5,$B$2:$B$36,0) -> 4 | D5: =IF(C5<=7,"Preferred",IF(C5<=21,"Approved","Conditional")) -> Preferred | E5: =MAX('Normalized Data'!B28:M28) -> 1 | F5: =MIN('Normalized Data'!B28:M28) -> 0.33333333 | G5: =INDEX(Weights!$A$2:$A$13,MATCH(MAX('Normalized Data'!B28:M28),'Normalized Data'!B28:M28,0)) -> serviceability and communicativeness | H5: =INDEX(Weights!$A$2:$A$13,MATCH(MIN('Normalized Data'!B28:M28),'Normalized Data'!B28:M28,0)) -> quality
A6: ='Normalized Data'!A26 -> 25 | B6: {=SUMPRODUCT('Normalized Data'!B26:M26,TRANSPOSE(Weights!$B$2:$B$13))} -> 0.61860163 | C6: =RANK(B6,$B$2:$B$36,0) -> 5 | D6: =IF(C6<=7,"Preferred",IF(C6<=21,"Approved","Conditional")) -> Preferred | E6: =MAX('Normalized Data'!B26:M26) -> 1 | F6: =MIN('Normalized Data'!B26:M26) -> 0 | G6: =INDEX(Weights!$A$2:$A$13,MATCH(MAX('Normalized Data'!B26:M26),'Normalized Data'!B26:M26,0)) -> reputation and competence | H6: =INDEX(Weights!$A$2:$A$13,MATCH(MIN('Normalized Data'!B26:M26),'Normalized Data'!B26:M26,0)) -> quality
A7: ='Normalized Data'!A14 -> 13 | B7: {=SUMPRODUCT('Normalized Data'!B14:M14,TRANSPOSE(Weights!$B$2:$B$13))} -> 0.60149593 | C7: =RANK(B7,$B$2:$B$36,0) -> 6 | D7: =IF(C7<=7,"Preferred",IF(C7<=21,"Approved","Conditional")) -> Preferred | E7: =MAX('Normalized Data'!B14:M14) -> 1 | F7: =MIN('Normalized Data'!B14:M14) -> 0.093333333 | G7: =INDEX(Weights!$A$2:$A$13,MATCH(MAX('Normalized Data'!B14:M14),'Normalized Data'!B14:M14,0)) -> conditions and method of payment | H7: =INDEX(Weights!$A$2:$A$13,MATCH(MIN('Normalized Data'!B14:M14),'Normalized Data'!B14:M14,0)) -> quantity
A8: ='Normalized Data'!A17 -> 16 | B8: {=SUMPRODUCT('Normalized Data'!B17:M17,TRANSPOSE(Weights!$B$2:$B$13))} -> 0.59533333 | C8: =RANK(B8,$B$2:$B$36,0) -> 7 | D8: =IF(C8<=7,"Preferred",IF(C8<=21,"Approved","Conditional")) -> Preferred | E8: =MAX('Normalized Data'!B17:M17) -> 1 | F8: =MIN('Normalized Data'!B17:M17) -> 0 | G8: =INDEX(Weights!$A$2:$A$13,MATCH(MAX('Normalized Data'!B17:M17),'Normalized Data'!B17:M17,0)) -> quality | H8: =INDEX(Weights!$A$2:$A$13,MATCH(MIN('Normalized Data'!B17:M17),'Normalized Data'!B17:M17,0)) -> location and traffic
A9: ='Normalized Data'!A12 -> 11 | B9: {=SUMPRODUCT('Normalized Data'!B12:M12,TRANSPOSE(Weights!$B$2:$B$13))} -> 0.57853659 | C9: =RANK(B9,$B$2:$B$36,0) -> 8 | D9: =IF(C9<=7,"Preferred",IF(C9<=21,"Approved","Conditional")) -> Approved | E9: =MAX('Normalized Data'!B12:M12) -> 1 | F9: =MIN('Normalized Data'!B12:M12) -> 0 | G9: =INDEX(Weights!$A$2:$A$13,MATCH(MAX('Normalized Data'!B12:M12),'Normalized Data'!B12:M12,0)) -> quality | H9: =INDEX(Weights!$A$2:$A$13,MATCH(MIN('Normalized Data'!B12:M12),'Normalized Data'!B12:M12,0)) -> quantity
A10: ='Normalized Data'!A27 -> 26 | B10: {=SUMPRODUCT('Normalized Data'!B27:M27,TRANSPOSE(Weights!$B$2:$B$13))} -> 0.57284553 | C10: =RANK(B10,$B$2:$B$36,0) -> 9 | D10: =IF(C10<=7,"Preferred",IF(C10<=21,"Approved","Conditional")) -> Approved | E10: =MAX('Normalized Data'!B27:M27) -> 1 | F10: =MIN('Normalized Data'!B27:M27) -> 0 | G10: =INDEX(Weights!$A$2:$A$13,MATCH(MAX('Normalized Data'!B27:M27),'Normalized Data'!B27:M27,0)) -> financial condition | H10: =INDEX(Weights!$A$2:$A$13,MATCH(MIN('Normalized Data'!B27:M27),'Normalized Data'!B27:M27,0)) -> quantity
A11: ='Normalized Data'!A5 -> 4 | B11: {=SUMPRODUCT('Normalized Data'!B5:M5,TRANSPOSE(Weights!$B$2:$B$13))} -> 0.55478049 | C11: =RANK(B11,$B$2:$B$36,0) -> 10 | D11: =IF(C11<=7,"Preferred",IF(C11<=21,"Approved","Conditional")) -> Approved | E11: =MAX('Normalized Data'!B5:M5) -> 1 | F11: =MIN('Normalized Data'!B5:M5) -> 0.11111111 | G11: =INDEX(Weights!$A$2:$A$13,MATCH(MAX('Normalized Data'!B5:M5),'Normalized Data'!B5:M5,0)) -> flexibility | H11: =INDEX(Weights!$A$2:$A$13,MATCH(MIN('Normalized Data'!B5:M5),'Normalized Data'!B5:M5,0)) -> delivery time
A12: ='Normalized Data'!A21 -> 20 | B12: {=SUMPRODUCT('Normalized Data'!B21:M21,TRANSPOSE(Weights!$B$2:$B$13))} -> 0.5355935 | C12: =RANK(B12,$B$2:$B$36,0) -> 11 | D12: =IF(C12<=7,"Preferred",IF(C12<=21,"Approved","Conditional")) -> Approved | E12: =MAX('Normalized Data'!B21:M21) -> 1 | F12: =MIN('Normalized Data'!B21:M21) -> 0.16666667 | G12: =INDEX(Weights!$A$2:$A$13,MATCH(MAX('Normalized Data'!B21:M21),'Normalized Data'!B21:M21,0)) -> price | H12: =INDEX(Weights!$A$2:$A$13,MATCH(MIN('Normalized Data'!B21:M21),'Normalized Data'!B21:M21,0)) -> serviceability and communicativeness
A13: ='Normalized Data'!A24 -> 23 | B13: {=SUMPRODUCT('Normalized Data'!B24:M24,TRANSPOSE(Weights!$B$2:$B$13))} -> 0.53435772 | C13: =RANK(B13,$B$2:$B$36,0) -> 12 | D13: =IF(C13<=7,"Preferred",IF(C13<=21,"Approved","Conditional")) -> Approved | E13: =MAX('Normalized Data'!B24:M24) -> 0.90243902 | F13: =MIN('Normalized Data'!B24:M24) -> 0.2 | G13: =INDEX(Weights!$A$2:$A$13,MATCH(MAX('Normalized Data'!B24:M24),'Normalized Data'!B24:M24,0)) -> location and traffic | H13: =INDEX(Weights!$A$2:$A$13,MATCH(MIN('Normalized Data'!B24:M24),'Normalized Data'!B24:M24,0)) -> condition of assets
A14: ='Normalized Data'!A16 -> 15 | B14: {=SUMPRODUCT('Normalized Data'!B16:M16,TRANSPOSE(Weights!$B$2:$B$13))} -> 0.52541463 | C14: =RANK(B14,$B$2:$B$36,0) -> 13 | D14: =IF(C14<=7,"Preferred",IF(C14<=21,"Approved","Conditional")) -> Approved | E14: =MAX('Normalized Data'!B16:M16) -> 0.8 | F14: =MIN('Normalized Data'!B16:M16) -> 0.2 | G14: =INDEX(Weights!$A$2:$A$13,MATCH(MAX('Normalized Data'!B16:M16),'Normalized Data'!B16:M16,0)) -> price | H14: =INDEX(Weights!$A$2:$A$13,MATCH(MIN('Normalized Data'!B16:M16),'Normalized Data'!B16:M16,0)) -> business results and employees
A15: ='Normalized Data'!A11 -> 10 | B15: {=SUMPRODUCT('Normalized Data'!B11:M11,TRANSPOSE(Weights!$B$2:$B$13))} -> 0.52295935 | C15: =RANK(B15,$B$2:$B$36,0) -> 14 | D15: =IF(C15<=7,"Preferred",IF(C15<=21,"Approved","Conditional")) -> Approved | E15: =MAX('Normalized Data'!B11:M11) -> 1 | F15: =MIN('Normalized Data'!B11:M11) -> 0.11111111 | G15: =INDEX(Weights!$A$2:$A$13,MATCH(MAX('Normalized Data'!B11:M11),'Normalized Data'!B11:M11,0)) -> serviceability and communicativeness | H15: =INDEX(Weights!$A$2:$A$13,MATCH(MIN('Normalized Data'!B11:M11),'Normalized Data'!B11:M11,0)) -> delivery time
A16: ='Normalized Data'!A22 -> 21 | B16: {=SUMPRODUCT('Normalized Data'!B22:M22,TRANSPOSE(Weights!$B$2:$B$13))} -> 0.52284553 | C16: =RANK(B16,$B$2:$B$36,0) -> 15 | D16: =IF(C16<=7,"Preferred",IF(C16<=21,"Approved","Conditional")) -> Approved | E16: =MAX('Normalized Data'!B22:M22) -> 1 | F16: =MIN('Normalized Data'!B22:M22) -> 0 | G16: =INDEX(Weights!$A$2:$A$13,MATCH(MAX('Normalized Data'!B22:M22),'Normalized Data'!B22:M22,0)) -> quality | H16: =INDEX(Weights!$A$2:$A$13,MATCH(MIN('Normalized Data'!B22:M22),'Normalized Data'!B22:M22,0)) -> conditions and method of payment
A17: ='Normalized Data'!A29 -> 28 | B17: {=SUMPRODUCT('Normalized Data'!B29:M29,TRANSPOSE(Weights!$B$2:$B$13))} -> 0.5102439 | C17: =RANK(B17,$B$2:$B$36,0) -> 16 | D17: =IF(C17<=7,"Preferred",IF(C17<=21,"Approved","Conditional")) -> Approved | E17: =MAX('Normalized Data'!B29:M29) -> 0.82439024 | F17: =MIN('Normalized Data'!B29:M29) -> 0.2 | G17: =INDEX(Weights!$A$2:$A$13,MATCH(MAX('Normalized Data'!B29:M29),'Normalized Data'!B29:M29,0)) -> location and traffic | H17: =INDEX(Weights!$A$2:$A$13,MATCH(MIN('Normalized Data'!B29:M29),'Normalized Data'!B29:M29,0)) -> condition of assets
A18: ='Normalized Data'!A18 -> 17 | B18: {=SUMPRODUCT('Normalized Data'!B18:M18,TRANSPOSE(Weights!$B$2:$B$13))} -> 0.49260163 | C18: =RANK(B18,$B$2:$B$36,0) -> 17 | D18: =IF(C18<=7,"Preferred",IF(C18<=21,"Approved","Conditional")) -> Approved | E18: =MAX('Normalized Data'!B18:M18) -> 1 | F18: =MIN('Normalized Data'!B18:M18) -> 0 | G18: =INDEX(Weights!$A$2:$A$13,MATCH(MAX('Normalized Data'!B18:M18),'Normalized Data'!B18:M18,0)) -> quantity | H18: =INDEX(Weights!$A$2:$A$13,MATCH(MIN('Normalized Data'!B18:M18),'Normalized Data'!B18:M18,0)) -> quality
A19: ='Normalized Data'!A23 -> 22 | B19: {=SUMPRODUCT('Normalized Data'!B23:M23,TRANSPOSE(Weights!$B$2:$B$13))} -> 0.48671545 | C19: =RANK(B19,$B$2:$B$36,0) -> 18 | D19: =IF(C19<=7,"Preferred",IF(C19<=21,"Approved","Conditional")) -> Approved | E19: =MAX('Normalized Data'!B23:M23) -> 1 | F19: =MIN('Normalized Data'!B23:M23) -> 0.16666667 | G19: =INDEX(Weights!$A$2:$A$13,MATCH(MAX('Normalized Data'!B23:M23),'Normalized Data'!B23:M23,0)) -> price | H19: =INDEX(Weights!$A$2:$A$13,MATCH(MIN('Normalized Data'!B23:M23),'Normalized Data'!B23:M23,0)) -> financial condition
A20: ='Normalized Data'!A34 -> 33 | B20: {=SUMPRODUCT('Normalized Data'!B34:M34,TRANSPOSE(Weights!$B$2:$B$13))} -> 0.46421138 | C20: =RANK(B20,$B$2:$B$36,0) -> 19 | D20: =IF(C20<=7,"Preferred",IF(C20<=21,"Approved","Conditional")) -> Approved | E20: =MAX('Normalized Data'!B34:M34) -> 0.88780488 | F20: =MIN('Normalized Data'!B34:M34) -> 0.16666667 | G20: =INDEX(Weights!$A$2:$A$13,MATCH(MAX('Normalized Data'!B34:M34),'Normalized Data'!B34:M34,0)) -> location and traffic | H20: =INDEX(Weights!$A$2:$A$13,MATCH(MIN('Normalized Data'!B34:M34),'Normalized Data'!B34:M34,0)) -> serviceability and communicativeness
A21: ='Normalized Data'!A30 -> 29 | B21: {=SUMPRODUCT('Normalized Data'!B30:M30,TRANSPOSE(Weights!$B$2:$B$13))} -> 0.43196748 | C21: =RANK(B21,$B$2:$B$36,0) -> 20 | D21: =IF(C21<=7,"Preferred",IF(C21<=21,"Approved","Conditional")) -> Approved | E21: =MAX('Normalized Data'!B30:M30) -> 1 | F21: =MIN('Normalized Data'!B30:M30) -> 0 | G21: =INDEX(Weights!$A$2:$A$13,MATCH(MAX('Normalized Data'!B30:M30),'Normalized Data'!B30:M30,0)) -> conditions and method of payment | H21: =INDEX(Weights!$A$2:$A$13,MATCH(MIN('Normalized Data'!B30:M30),'Normalized Data'!B30:M30,0)) -> serviceability and communicativeness
A22: ='Normalized Data'!A35 -> 34 | B22: {=SUMPRODUCT('Normalized Data'!B35:M35,TRANSPOSE(Weights!$B$2:$B$13))} -> 0.43196748 | C22: =RANK(B22,$B$2:$B$36,0) -> 20 | D22: =IF(C22<=7,"Preferred",IF(C22<=21,"Approved","Conditional")) -> Approved | E22: =MAX('Normalized Data'!B35:M35) -> 0.8 | F22: =MIN('Normalized Data'!B35:M35) -> 0.04 | G22: =INDEX(Weights!$A$2:$A$13,MATCH(MAX('Normalized Data'!B35:M35),'Normalized Data'!B35:M35,0)) -> price | H22: =INDEX(Weights!$A$2:$A$13,MATCH(MIN('Normalized Data'!B35:M35),'Normalized Data'!B35:M35,0)) -> quantity
A23: ='Normalized Data'!A4 -> 3 | B23: {=SUMPRODUCT('Normalized Data'!B4:M4,TRANSPOSE(Weights!$B$2:$B$13))} -> 0.43126829 | C23: =RANK(B23,$B$2:$B$36,0) -> 22 | D23: =IF(C23<=7,"Preferred",IF(C23<=21,"Approved","Conditional")) -> Conditional | E23: =MAX('Normalized Data'!B4:M4) -> 1 | F23: =MIN('Normalized Data'!B4:M4) -> 0 | G23: =INDEX(Weights!$A$2:$A$13,MATCH(MAX('Normalized Data'!B4:M4),'Normalized Data'!B4:M4,0)) -> condition of assets | H23: =INDEX(Weights!$A$2:$A$13,MATCH(MIN('Normalized Data'!B4:M4),'Normalized Data'!B4:M4,0)) -> quality
A24: ='Normalized Data'!A20 -> 19 | B24: {=SUMPRODUCT('Normalized Data'!B20:M20,TRANSPOSE(Weights!$B$2:$B$13))} -> 0.42386992 | C24: =RANK(B24,$B$2:$B$36,0) -> 23 | D24: =IF(C24<=7,"Preferred",IF(C24<=21,"Approved","Conditional")) -> Conditional | E24: =MAX('Normalized Data'!B20:M20) -> 1 | F24: =MIN('Normalized Data'!B20:M20) -> 0 | G24: =INDEX(Weights!$A$2:$A$13,MATCH(MAX('Normalized Data'!B20:M20),'Normalized Data'!B20:M20,0)) -> quality | H24: =INDEX(Weights!$A$2:$A$13,MATCH(MIN('Normalized Data'!B20:M20),'Normalized Data'!B20:M20,0)) -> serviceability and communicativeness
A25: ='Normalized Data'!A36 -> 35 | B25: {=SUMPRODUCT('Normalized Data'!B36:M36,TRANSPOSE(Weights!$B$2:$B$13))} -> 0.39921951 | C25: =RANK(B25,$B$2:$B$36,0) -> 24 | D25: =IF(C25<=7,"Preferred",IF(C25<=21,"Approved","Conditional")) -> Conditional | E25: =MAX('Normalized Data'!B36:M36) -> 1 | F25: =MIN('Normalized Data'!B36:M36) -> 0 | G25: =INDEX(Weights!$A$2:$A$13,MATCH(MAX('Normalized Data'!B36:M36),'Normalized Data'!B36:M36,0)) -> price | H25: =INDEX(Weights!$A$2:$A$13,MATCH(MIN('Normalized Data'!B36:M36),'Normalized Data'!B36:M36,0)) -> quality
A26: ='Normalized Data'!A7 -> 6 | B26: {=SUMPRODUCT('Normalized Data'!B7:M7,TRANSPOSE(Weights!$B$2:$B$13))} -> 0.38871545 | C26: =RANK(B26,$B$2:$B$36,0) -> 25 | D26: =IF(C26<=7,"Preferred",IF(C26<=21,"Approved","Conditional")) -> Conditional | E26: =MAX('Normalized Data'!B7:M7) -> 1 | F26: =MIN('Normalized Data'!B7:M7) -> 0 | G26: =INDEX(Weights!$A$2:$A$13,MATCH(MAX('Normalized Data'!B7:M7),'Normalized Data'!B7:M7,0)) -> financial condition | H26: =INDEX(Weights!$A$2:$A$13,MATCH(MIN('Normalized Data'!B7:M7),'Normalized Data'!B7:M7,0)) -> conditions and method of payment
A27: ='Normalized Data'!A2 -> 1 | B27: {=SUMPRODUCT('Normalized Data'!B2:M2,TRANSPOSE(Weights!$B$2:$B$13))} -> 0.37029268 | C27: =RANK(B27,$B$2:$B$36,0) -> 26 | D27: =IF(C27<=7,"Preferred",IF(C27<=21,"Approved","Conditional")) -> Conditional | E27: =MAX('Normalized Data'!B2:M2) -> 0.82926829 | F27: =MIN('Normalized Data'!B2:M2) -> 0 | G27: =INDEX(Weights!$A$2:$A$13,MATCH(MAX('Normalized Data'!B2:M2),'Normalized Data'!B2:M2,0)) -> location and traffic | H27: =INDEX(Weights!$A$2:$A$13,MATCH(MIN('Normalized Data'!B2:M2),'Normalized Data'!B2:M2,0)) -> serviceability and communicativeness
A28: ='Normalized Data'!A9 -> 8 | B28: {=SUMPRODUCT('Normalized Data'!B9:M9,TRANSPOSE(Weights!$B$2:$B$13))} -> 0.3655935 | C28: =RANK(B28,$B$2:$B$36,0) -> 27 | D28: =IF(C28<=7,"Preferred",IF(C28<=21,"Approved","Conditional")) -> Conditional | E28: =MAX('Normalized Data'!B9:M9) -> 0.77777778 | F28: =MIN('Normalized Data'!B9:M9) -> 0 | G28: =INDEX(Weights!$A$2:$A$13,MATCH(MAX('Normalized Data'!B9:M9),'Normalized Data'!B9:M9,0)) -> delivery time | H28: =INDEX(Weights!$A$2:$A$13,MATCH(MIN('Normalized Data'!B9:M9),'Normalized Data'!B9:M9,0)) -> conditions and method of payment
A29: ='Normalized Data'!A19 -> 18 | B29: {=SUMPRODUCT('Normalized Data'!B19:M19,TRANSPOSE(Weights!$B$2:$B$13))} -> 0.35666667 | C29: =RANK(B29,$B$2:$B$36,0) -> 28 | D29: =IF(C29<=7,"Preferred",IF(C29<=21,"Approved","Conditional")) -> Conditional | E29: =MAX('Normalized Data'!B19:M19) -> 0.8 | F29: =MIN('Normalized Data'!B19:M19) -> 0 | G29: =INDEX(Weights!$A$2:$A$13,MATCH(MAX('Normalized Data'!B19:M19),'Normalized Data'!B19:M19,0)) -> location and traffic | H29: =INDEX(Weights!$A$2:$A$13,MATCH(MIN('Normalized Data'!B19:M19),'Normalized Data'!B19:M19,0)) -> conditions and method of payment
A30: ='Normalized Data'!A13 -> 12 | B30: {=SUMPRODUCT('Normalized Data'!B13:M13,TRANSPOSE(Weights!$B$2:$B$13))} -> 0.34756098 | C30: =RANK(B30,$B$2:$B$36,0) -> 29 | D30: =IF(C30<=7,"Preferred",IF(C30<=21,"Approved","Conditional")) -> Conditional | E30: =MAX('Normalized Data'!B13:M13) -> 1 | F30: =MIN('Normalized Data'!B13:M13) -> 0 | G30: =INDEX(Weights!$A$2:$A$13,MATCH(MAX('Normalized Data'!B13:M13),'Normalized Data'!B13:M13,0)) -> conditions and method of payment | H30: =INDEX(Weights!$A$2:$A$13,MATCH(MIN('Normalized Data'!B13:M13),'Normalized Data'!B13:M13,0)) -> quality
A31: ='Normalized Data'!A31 -> 30 | B31: {=SUMPRODUCT('Normalized Data'!B31:M31,TRANSPOSE(Weights!$B$2:$B$13))} -> 0.34373984 | C31: =RANK(B31,$B$2:$B$36,0) -> 30 | D31: =IF(C31<=7,"Preferred",IF(C31<=21,"Approved","Conditional")) -> Conditional | E31: =MAX('Normalized Data'!B31:M31) -> 0.70731707 | F31: =MIN('Normalized Data'!B31:M31) -> 0 | G31: =INDEX(Weights!$A$2:$A$13,MATCH(MAX('Normalized Data'!B31:M31),'Normalized Data'!B31:M31,0)) -> location and traffic | H31: =INDEX(Weights!$A$2:$A$13,MATCH(MIN('Normalized Data'!B31:M31),'Normalized Data'!B31:M31,0)) -> conditions and method of payment
A32: ='Normalized Data'!A6 -> 5 | B32: {=SUMPRODUCT('Normalized Data'!B6:M6,TRANSPOSE(Weights!$B$2:$B$13))} -> 0.32569106 | C32: =RANK(B32,$B$2:$B$36,0) -> 31 | D32: =IF(C32<=7,"Preferred",IF(C32<=21,"Approved","Conditional")) -> Conditional | E32: =MAX('Normalized Data'!B6:M6) -> 0.90243902 | F32: =MIN('Normalized Data'!B6:M6) -> 0 | G32: =INDEX(Weights!$A$2:$A$13,MATCH(MAX('Normalized Data'!B6:M6),'Normalized Data'!B6:M6,0)) -> location and traffic | H32: =INDEX(Weights!$A$2:$A$13,MATCH(MIN('Normalized Data'!B6:M6),'Normalized Data'!B6:M6,0)) -> flexibility
A33: ='Normalized Data'!A32 -> 31 | B33: {=SUMPRODUCT('Normalized Data'!B32:M32,TRANSPOSE(Weights!$B$2:$B$13))} -> 0.30734959 | C33: =RANK(B33,$B$2:$B$36,0) -> 32 | D33: =IF(C33<=7,"Preferred",IF(C33<=21,"Approved","Conditional")) -> Conditional | E33: =MAX('Normalized Data'!B32:M32) -> 1 | F33: =MIN('Normalized Data'!B32:M32) -> 0 | G33: =INDEX(Weights!$A$2:$A$13,MATCH(MAX('Normalized Data'!B32:M32),'Normalized Data'!B32:M32,0)) -> price | H33: =INDEX(Weights!$A$2:$A$13,MATCH(MIN('Normalized Data'!B32:M32),'Normalized Data'!B32:M32,0)) -> quality
A34: ='Normalized Data'!A33 -> 32 | B34: {=SUMPRODUCT('Normalized Data'!B33:M33,TRANSPOSE(Weights!$B$2:$B$13))} -> 0.29533333 | C34: =RANK(B34,$B$2:$B$36,0) -> 33 | D34: =IF(C34<=7,"Preferred",IF(C34<=21,"Approved","Conditional")) -> Conditional | E34: =MAX('Normalized Data'!B33:M33) -> 1 | F34: =MIN('Normalized Data'!B33:M33) -> 0 | G34: =INDEX(Weights!$A$2:$A$13,MATCH(MAX('Normalized Data'!B33:M33),'Normalized Data'!B33:M33,0)) -> location and traffic | H34: =INDEX(Weights!$A$2:$A$13,MATCH(MIN('Normalized Data'!B33:M33),'Normalized Data'!B33:M33,0)) -> reputation and competence
A35: ='Normalized Data'!A8 -> 7 | B35: {=SUMPRODUCT('Normalized Data'!B8:M8,TRANSPOSE(Weights!$B$2:$B$13))} -> 0.27970732 | C35: =RANK(B35,$B$2:$B$36,0) -> 34 | D35: =IF(C35<=7,"Preferred",IF(C35<=21,"Approved","Conditional")) -> Conditional | E35: =MAX('Normalized Data'!B8:M8) -> 0.77073171 | F35: =MIN('Normalized Data'!B8:M8) -> 0 | G35: =INDEX(Weights!$A$2:$A$13,MATCH(MAX('Normalized Data'!B8:M8),'Normalized Data'!B8:M8,0)) -> location and traffic | H35: =INDEX(Weights!$A$2:$A$13,MATCH(MIN('Normalized Data'!B8:M8),'Normalized Data'!B8:M8,0)) -> conditions and method of payment
A36: ='Normalized Data'!A3 -> 2 | B36: {=SUMPRODUCT('Normalized Data'!B3:M3,TRANSPOSE(Weights!$B$2:$B$13))} -> 0.24980488 | C36: =RANK(B36,$B$2:$B$36,0) -> 35 | D36: =IF(C36<=7,"Preferred",IF(C36<=21,"Approved","Conditional")) -> Conditional | E36: =MAX('Normalized Data'!B3:M3) -> 0.7804878 | F36: =MIN('Normalized Data'!B3:M3) -> 0 | G36: =INDEX(Weights!$A$2:$A$13,MATCH(MAX('Normalized Data'!B3:M3),'Normalized Data'!B3:M3,0)) -> location and traffic | H36: =INDEX(Weights!$A$2:$A$13,MATCH(MIN('Normalized Data'!B3:M3),'Normalized Data'!B3:M3,0)) -> quality

Sheet Dashboard
B2: SUPPLIER EVALUATION DASHBOARD
B3: Multi-Criteria Decision Model - 35 Suppliers - 12 Evaluation Criteria
B5: TOTAL SUPPLIERS | E5: PREFERRED | H5: APPROVED | K5: CONDITIONAL
B6: =COUNTA(Scoring!$A$2:$A$36) -> 35 | E6: =COUNTIF(Scoring!$D$2:$D$36,"Preferred") -> 7 | H6: =COUNTIF(Scoring!$D$2:$D$36,"Approved") -> 14 | K6: =COUNTIF(Scoring!$D$2:$D$36,"Conditional") -> 14
B8: evaluated suppliers | E8: top tier suppliers | H8: qualified suppliers | K8: require improvement
B10: MARKET OVERVIEW
B11: Criteria | G11: Avg Score | J11: Market Strength
B12: =Weights!A2 -> quality | G12: =AVERAGE(OFFSET('Normalized Data'!$B$2:$B$36,0,ROW()-12)) -> 0.45714286 | J12: =IF(G12>=0.7,"Strong",IF(G12>=0.4,"Moderate","Weak")) -> Moderate
B13: =Weights!A3 -> quantity | G13: =AVERAGE(OFFSET('Normalized Data'!$B$2:$B$36,0,ROW()-12)) -> 0.312 | J13: =IF(G13>=0.7,"Strong",IF(G13>=0.4,"Moderate","Weak")) -> Weak
B14: =Weights!A4 -> conditions and method of payment | G14: =AVERAGE(OFFSET('Normalized Data'!$B$2:$B$36,0,ROW()-12)) -> 0.47857143 | J14: =IF(G14>=0.7,"Strong",IF(G14>=0.4,"Moderate","Weak")) -> Moderate
B15: =Weights!A5 -> serviceability and communicativeness | G15: =AVERAGE(OFFSET('Normalized Data'!$B$2:$B$36,0,ROW()-12)) -> 0.49047619 | J15: =IF(G15>=0.7,"Strong",IF(G15>=0.4,"Moderate","Weak")) -> Moderate
B16: =Weights!A6 -> reputation and competence | G16: =AVERAGE(OFFSET('Normalized Data'!$B$2:$B$36,0,ROW()-12)) -> 0.43428571 | J16: =IF(G16>=0.7,"Strong",IF(G16>=0.4,"Moderate","Weak")) -> Moderate
B17: =Weights!A7 -> flexibility | G17: =AVERAGE(OFFSET('Normalized Data'!$B$2:$B$36,0,ROW()-12)) -> 0.46666667 | J17: =IF(G17>=0.7,"Strong",IF(G17>=0.4,"Moderate","Weak")) -> Moderate
B18: =Weights!A8 -> financial condition | G18: =AVERAGE(OFFSET('Normalized Data'!$B$2:$B$36,0,ROW()-12)) -> 0.47142857 | J18: =IF(G18>=0.7,"Strong",IF(G18>=0.4,"Moderate","Weak")) -> Moderate
B19: =Weights!A9 -> condition of assets | G19: =AVERAGE(OFFSET('Normalized Data'!$B$2:$B$36,0,ROW()-12)) -> 0.54285714 | J19: =IF(G19>=0.7,"Strong",IF(G19>=0.4,"Moderate","Weak")) -> Moderate
B20: =Weights!A10 -> business results and employees | G20: =AVERAGE(OFFSET('Normalized Data'!$B$2:$B$36,0,ROW()-12)) -> 0.44 | J20: =IF(G20>=0.7,"Strong",IF(G20>=0.4,"Moderate","Weak")) -> Moderate
B21: =Weights!A11 -> price | G21: =AVERAGE(OFFSET('Normalized Data'!$B$2:$B$36,0,ROW()-12)) -> 0.53714286 | J21: =IF(G21>=0.7,"Strong",IF(G21>=0.4,"Moderate","Weak")) -> Moderate
B22: =Weights!A12 -> delivery time | G22: =AVERAGE(OFFSET('Normalized Data'!$B$2:$B$36,0,ROW()-12)) -> 0.45714286 | J22: =IF(G22>=0.7,"Strong",IF(G22>=0.4,"Moderate","Weak")) -> Moderate
B23: =Weights!A13 -> location and traffic | G23: =AVERAGE(OFFSET('Normalized Data'!$B$2:$B$36,0,ROW()-12)) -> 0.75958188 | J23: =IF(G23>=0.7,"Strong",IF(G23>=0.4,"Moderate","Weak")) -> Strong
B25: TOP TIER SUPPLIERS
B26: =Scoring!A1 -> Supplier ID | D26: Score | E26: Best Feature | H26: Score | I26: Weakness | L26: Score
B27: =INDEX(Scoring!$A$2:$A$36,MATCH(1,Scoring!$C$2:$C$36,0)) -> 9 | D27: =VLOOKUP(B27, Scoring!A2:B36, 2, FALSE) -> 0.70421138 | E27: =VLOOKUP(B27, Scoring!A2:H36, 7, FALSE) -> quality | H27: =VLOOKUP(B27, Scoring!A2:H36, 5, FALSE) -> 1 | I27: =VLOOKUP(B27, Scoring!A2:H36, 8, FALSE) -> business results and employees | L27: =VLOOKUP(B27, Scoring!A2:H36, 6, FALSE) -> 0.2
B28: =INDEX(Scoring!$A$2:$A$36,MATCH(2,Scoring!$C$2:$C$36,0)) -> 24 | D28: =VLOOKUP(B28, Scoring!A3:B37, 2, FALSE) -> 0.68053659 | E28: =VLOOKUP(B28, Scoring!A3:H37, 7, FALSE) -> reputation and competence | H28: =VLOOKUP(B28, Scoring!A3:H37, 5, FALSE) -> 1 | I28: =VLOOKUP(B28, Scoring!A3:H37, 8, FALSE) -> quantity | L28: =VLOOKUP(B28, Scoring!A3:H37, 6, FALSE) -> 0.30666667
B29: =INDEX(Scoring!$A$2:$A$36,MATCH(3,Scoring!$C$2:$C$36,0)) -> 14 | D29: =VLOOKUP(B29, Scoring!A4:B38, 2, FALSE) -> 0.65834146 | E29: =VLOOKUP(B29, Scoring!A4:H38, 7, FALSE) -> conditions and method of payment | H29: =VLOOKUP(B29, Scoring!A4:H38, 5, FALSE) -> 1 | I29: =VLOOKUP(B29, Scoring!A4:H38, 8, FALSE) -> quantity | L29: =VLOOKUP(B29, Scoring!A4:H38, 6, FALSE) -> 0.44
B30: =INDEX(Scoring!$A$2:$A$36,MATCH(4,Scoring!$C$2:$C$36,0)) -> 27 | D30: =VLOOKUP(B30, Scoring!A5:B39, 2, FALSE) -> 0.62347967 | E30: =VLOOKUP(B30, Scoring!A5:H39, 7, FALSE) -> serviceability and communicativeness | H30: =VLOOKUP(B30, Scoring!A5:H39, 5, FALSE) -> 1 | I30: =VLOOKUP(B30, Scoring!A5:H39, 8, FALSE) -> quality | L30: =VLOOKUP(B30, Scoring!A5:H39, 6, FALSE) -> 0.33333333
B31: =INDEX(Scoring!$A$2:$A$36,MATCH(5,Scoring!$C$2:$C$36,0)) -> 25 | D31: =VLOOKUP(B31, Scoring!A6:B40, 2, FALSE) -> 0.61860163 | E31: =VLOOKUP(B31, Scoring!A6:H40, 7, FALSE) -> reputation and competence | H31: =VLOOKUP(B31, Scoring!A6:H40, 5, FALSE) -> 1 | I31: =VLOOKUP(B31, Scoring!A6:H40, 8, FALSE) -> quality | L31: =VLOOKUP(B31, Scoring!A6:H40, 6, FALSE) -> 0
B32: =INDEX(Scoring!$A$2:$A$36,MATCH(6,Scoring!$C$2:$C$36,0)) -> 13 | D32: =VLOOKUP(B32, Scoring!A7:B41, 2, FALSE) -> 0.60149593 | E32: =VLOOKUP(B32, Scoring!A7:H41, 7, FALSE) -> conditions and method of payment | H32: =VLOOKUP(B32, Scoring!A7:H41, 5, FALSE) -> 1 | I32: =VLOOKUP(B32, Scoring!A7:H41, 8, FALSE) -> quantity | L32: =VLOOKUP(B32, Scoring!A7:H41, 6, FALSE) -> 0.093333333
B33: =INDEX(Scoring!$A$2:$A$36,MATCH(7,Scoring!$C$2:$C$36,0)) -> 16 | D33: =VLOOKUP(B33, Scoring!A8:B42, 2, FALSE) -> 0.59533333 | E33: =VLOOKUP(B33, Scoring!A8:H42, 7, FALSE) -> quality | H33: =VLOOKUP(B33, Scoring!A8:H42, 5, FALSE) -> 1 | I33: =VLOOKUP(B33, Scoring!A8:H42, 8, FALSE) -> location and traffic | L33: =VLOOKUP(B33, Scoring!A8:H42, 6, FALSE) -> 0
B35: Data source: Dynamic Inventory Analytics · Kaggle · Kaizen Analytics · kaggle.com/datasets/andrewniko/dynamic-inventory-dataset-kaizen-analytics
